{
  "table": [
    {
      "caption": "Magic Item Sale Complications",
      "colLabels": [
        "d6",
        "Complication"
      ],
      "colStyles": [
        "col-2 text-center",
        "col-10"
      ],
      "rows": [
        [
          "1",
          "Your enemy secretly arranges to buy the item to use it against you.*"
        ],
        [
          "2",
          "A thieves' guild, alerted to the sale, attempts to steal your item.*"
        ],
        [
          "3",
          "A foe circulates rumors that your item is a fake.*"
        ],
        [
          "4",
          "A sorcerer claims your item as a birthright and demands you hand it over."
        ],
        [
          "5",
          "Your item's previous owner, or surviving allies of the owner, vow to retake the item by force."
        ],
        [
          "6",
          "The buyer is murdered before the sale is finalized.*"
        ]
      ],
      "footnotes": [
        "*Might involve a rival"
      ],
      "name": "Magic Item Sale Complications",
      "page": 133,
      "source": "XGE",
      "chapter": {
        "name": "Dungeon Master's Tools",
        "ordinal": {
          "type": "chapter",
          "identifier": 2
        },
        "index": 2
      }
    }
  ],
  "top_category": "Treasure & Loot",
  "sub_category": "Magic Items",
  "tags": [
    "Magic Item Sale",
    "Complications",
    "Dungeon Master's Tools",
    "Table",
    "Roleplay"
  ]
}